Workbook

Sheet Instrucciones
A1: Libro de trabajo de la AE2 · Proyecto Final de Grado 2026
A2: Universidad de la Cuenca del Plata · Ingeniería en Sistemas de Información · Comisión A · Sede Posadas · Docente Titular: PosDr. Darío Ezequiel Díaz · ISI-PFG-2026C2-AE2-v02
A3: Autor: Thiago Martino Leal (DNI 45.775.785) · Proyecto: Sistema de Procesamiento de Transacciones orientado a Alojamientos transitorios por hora (Motel C.C.)
A5: Para qué sirve este libro | B5: Reúne, en un solo archivo versionable, los instrumentos de la Unidad Dos que producen el Capítulo III y alimentan los Capítulos V y X: el catálogo de requisitos, la matriz de trazabilidad, el filtro de entidades, el registro de reglas, el glosario, el plan de iteraciones y el dimensionamiento de recursos. La hoja «Panel» controla sola el estado de completitud y avisa qué falta.
A6: Dónde se guarda | B6: En el repositorio del equipo, carpeta /03-requisitos, con la nomenclatura de la cátedra: AAAAMMDD_CatalogoRequisitos_Equipo_vN.xlsx (archivo actual: 20261001_CatalogoRequisitos_ThiagoLeal_v2.xlsx). Se versiona cada vez que se cierra un bloque de filas, no una sola vez antes de la entrega.
A7: Qué celdas se completan | B7: Todas las celdas blancas y grises de cada hoja, a partir de la fila 5. Las filas sombreadas en ocre son ejemplos resueltos sobre el caso conductor «Santa Ana»: se leen, no se copian, y se borran antes de entregar. Las columnas de control, sombreadas en amarillo, contienen fórmulas: no se escriben.
A8: Cómo se usan las listas desplegables | B8: Las columnas de tipo, prioridad y estado admiten sólo los valores de la lista. Si un valor es rechazado, es porque la categoría no corresponde a la clasificación de la cátedra.
A9: Qué mira la corrección | B9: Que cada requisito tenga sus seis campos, que su criterio de aceptación sea un procedimiento ejecutable por un tercero, que la trazabilidad cierre en doble vía y que el conjunto de los requisitos «Must» coincida con el producto mínimo viable del apartado V.5.
A10: Orden de trabajo sugerido | B10: 1) Entidades y Reglas, en el taller. 2) Trazabilidad, con los hallazgos de la AE1 codificados H-01, H-02… 3) Catálogo, derivando requisitos de esos hallazgos. 4) Sesión de validación con el referente y actualización de los estados. 5) Iteraciones y Recursos, ya con el catálogo cerrado.
A11: Advertencia | B11: Ante divergencia entre este libro y la Consigna ISI-PFG-2026C2-AE2-v02, prevalece la consigna. Ante divergencia entre la consigna y la Resolución Rectoral UCP N.º 97/23, prevalece la Resolución.
A13: Leyenda de colores
A14: Ocre | B14: Fila de ejemplo resuelta sobre el caso «Santa Ana». Se borra antes de entregar.
A15: Amarillo | B15: Celda con fórmula de control. No se escribe.
A16: Blanco y gris | B16: Celdas que completa el estudiante.

Sheet Catálogo
A1: Catálogo de requisitos · apartado III.5 del informe
A2: Una fila por requisito, con los seis campos completos. Regla de cómputo: un requisito sin criterio de aceptación comprobable no se computa, por bien redactado que esté.
A4: ID | B4: Enunciado | C4: Tipo | D4: Categoría (si es no funcional) | E4: Prioridad | F4: Motivo de la prioridad | G4: Criterio de aceptación (condición, acción, resultado con valores) | H4: Trazabilidad (H-xx o acta) | I4: Estado de validación | J4: Iteración prevista | K4: ¿Integra el MVP? | L4: Control de completitud
A5: RF-01 | B5: El sistema visualiza en una grilla interactiva el estado en tiempo real de las 13 habitaciones con codificación cromática. | C5: Funcional | E5: Must | F5: Sustituye el tablero de madera físico y constituye la interfaz central de conserjería con fricción cero. | G5: Condición inicial: Sesión activa como conserje. Acción: Cargar vista principal. Resultado: Se despliegan 13 tarjetas con estado cromático (Libre=verde, Ocupada=rojo, Limpieza=amarillo) en un tiempo <= 500 ms. | H5: H-01 · observación en ventanilla | I5: Validado | J5: 2 | K5: Sí | L5: =IF(AND(A5<>"",B5<>"",C5<>"",E5<>"",F5<>"",G5<>"",H5<>""),"Fila completa","Incompleto") -> Fila completa
A6: RF-02 | B6: El sistema registra el inicio de un turno asignando una habitación libre y fijando el timestamp de ingreso automático. | C6: Funcional | E6: Must | F6: Núcleo transaccional del servicio por hora; elimina la alteración manual de horarios en fichas de papel. | G6: Condición inicial: Habitación en estado Libre. Acción: Conserje ingresa código vehicular transitorio y confirma. Resultado: Turno pasa a En Curso, habitación a Ocupada y cronómetro inicia con timestamp del servidor. | H6: H-02 · fichas de papel manuscritas | I6: Validado | J6: 2 | K6: Sí | L6: =IF(AND(A6<>"",B6<>"",C6<>"",E6<>"",F6<>"",G6<>"",H6<>""),"Fila completa","Incompleto") -> Fila completa
A7: RF-03 | B7: El sistema calcula el importe del turno aplicando la tarifa base y adicionando sobreturnos transcurridos según el algoritmo de fraccionamiento. | C7: Funcional | E7: Must | F7: Automatiza la liquidación financiera y elimina cobros y sumas manuales erróneas en ventanilla. | G7: Condición inicial: Turno activo excede los 120 minutos base. Acción: Presionar liquidar turno. Resultado: El sistema aplica tarifa base ($8.000) más recargo proporcional por fracción de 30 min ($2.500 c/u) según RN-DER-01 con 0% de error de cálculo. | H7: H-03 · demoras y sumas manuales | I7: Validado | J7: 2 | K7: Sí | L7: =IF(AND(A7<>"",B7<>"",C7<>"",E7<>"",F7<>"",G7<>"",H7<>""),"Fila completa","Incompleto") -> Fila completa
A8: RF-04 | B8: El sistema registra el despacho de consumiciones de minibar vinculándolas al turno y descontando el stock de forma atómica. | C8: Funcional | E8: Must | F8: Controla el inventario de bebidas/golosinas y evita pérdidas de productos entregados a habitaciones. | G8: Condición inicial: Turno en curso y artículo con stock >= 1. Acción: Seleccionar artículo y cantidad, confirmar despacho. Resultado: Se inserta Detalle_Consumo, se adiciona el subtotal a la cuenta del turno y se descuenta el stock en la misma transacción ACID. | H8: H-04 · faltantes de stock en cuadernos | I8: Validado | J8: 2 | K8: Sí | L8: =IF(AND(A8<>"",B8<>"",C8<>"",E8<>"",F8<>"",G8<>"",H8<>""),"Fila completa","Incompleto") -> Fila completa
A9: RF-05 | B9: El sistema bloquea el despacho de artículos de minibar cuando la cantidad solicitada excede el stock disponible. | C9: Funcional | E9: Must | F9: Aplica la regla RN-EXI-02 evitando registros ficticios y descalces de inventario en almacén. | G9: Condición inicial: Artículo con stock = 0 en sistema. Acción: Intentar despachar el producto a una habitación. Resultado: La interfaz bloquea la confirmación con mensaje «Stock insuficiente» y no genera registros en base de datos. | H9: H-05 · desajustes y mermas al arqueo | I9: Validado | J9: 2 | K9: Sí | L9: =IF(AND(A9<>"",B9<>"",C9<>"",E9<>"",F9<>"",G9<>"",H9<>""),"Fila completa","Incompleto") -> Fila completa
A10: RF-06 | B10: El sistema registra cobros discriminando importes en efectivo físico y transferencias electrónicas respaldadas por cupón POSNET. | C10: Funcional | E10: Must | F10: Permite conciliar pagos mixtos y auditar cupones digitales frente a la recaudación física. | G10: Condición inicial: Turno en etapa de liquidación. Acción: Asentar desglose de efectivo y número de cupón POSNET. Resultado: Se crean los registros en tabla Pago, el saldo pendiente de la habitación pasa a $0 y se emite constancia de cobro. | H10: H-06 · descalce de efectivo y MP | I10: Validado | J10: 2 | K10: Sí | L10: =IF(AND(A10<>"",B10<>"",C10<>"",E10<>"",F10<>"",G10<>"",H10<>""),"Fila completa","Incompleto") -> Fila completa
A11: RF-07 | B11: El sistema impide la transición de la habitación a estado En Limpieza si el turno registra saldo monetario pendiente. | C11: Funcional | E11: Must | F11: Aplica la regla RN-EXI-03 erradicando la fuga operativa de turnos liberados sin haber cobrado. | G11: Condición inicial: Turno liquidado con saldo adeudado > $0. Acción: Conserje presiona botón liberar a limpieza. Resultado: Sistema rechaza la operación, mantiene habitación en Ocupada y resalta advertencia visual de deuda pendiente. | H11: H-07 · fuga de turnos impagos | I11: Validado | J11: 2 | K11: Sí | L11: =IF(AND(A11<>"",B11<>"",C11<>"",E11<>"",F11<>"",G11<>"",H11<>""),"Fila completa","Incompleto") -> Fila completa
A12: RF-08 | B12: El sistema procesa el Cierre de Caja Ciego de 8 horas sin exhibir los totales calculados por el sistema antes del arqueo. | C12: Funcional | E12: Must | F12: Eslabón crítico contra la Tasa de Discrepancia de Caja (TDC) del 10%; anula el ajuste manual de billetes. | G12: Condición inicial: Culminación de guardia de 8 horas. Acción: Operador saliente ingresa recuento físico de efectivo y cupones a ciegas. Resultado: Sesión persiste en log inmutable, calcula desvío y bloquea la interfaz de la guardia finalizada. | H12: H-08 · demora de 17 min y ajuste manual | I12: Validado | J12: 2 | K12: Sí | L12: =IF(AND(A12<>"",B12<>"",C12<>"",E12<>"",F12<>"",G12<>"",H12<>""),"Fila completa","Incompleto") -> Fila completa
A13: RF-09 | B13: El sistema calcula y categoriza la discrepancia de caja comparando valores declarados frente a transacciones registradas. | C13: Funcional | E13: Must | F13: Métrica objetiva de control financiero exigida por gerencia para evaluar la responsabilidad de cada conserje. | G13: Condición inicial: Arqueo ciego confirmado. Acción: Sistema ejecuta RN-DER-03. Resultado: Se persiste la diferencia monetaria exacta (Declarado - Sistema) y se clasifica como Correcto ($0), Faltante (<$0) o Sobrante (>$0). | H13: H-09 · TDC histórica del 10% semanal | I13: Validado | J13: 2 | K13: Sí | L13: =IF(AND(A13<>"",B13<>"",C13<>"",E13<>"",F13<>"",G13<>"",H13<>""),"Fila completa","Incompleto") -> Fila completa
A14: RF-10 | B14: El sistema genera un comprobante de arqueo de caja en formato PDF consolidando el detalle de la guardia. | C14: Funcional | E14: Should | F14: Proporciona respaldo físico impreso para rendición contable y sobre de resguardo gerencial. | G14: Condición inicial: Arqueo inmutable cerrado. Acción: Hacer clic en botón Exportar PDF. Resultado: Se genera y descarga documento PDF estructurado con resumen de turnos, medios de pago y desvíos en < 2 segundos. | H14: H-10 · extravío de planillas manuscritas | I14: Validado | J14: 3 | K14: No | L14: =IF(AND(A14<>"",B14<>"",C14<>"",E14<>"",F14<>"",G14<>"",H14<>""),"Fila completa","Incompleto") -> Fila completa
A15: RF-11 | B15: El sistema permite al administrador modificar tarifas horarias y precios de venta de artículos de minibar. | C15: Funcional | E15: Should | F15: Permite actualizar precios ante inflación sin tocar el código fuente; turnos pasados conservan tarifa histórica. | G15: Condición inicial: Sesión con rol admin. Acción: Actualizar valor de tarifa o artículo en panel de gestión. Resultado: Los nuevos valores rigen para turnos futuros, preservando inalterados los registros históricos liquidados. | H15: H-11 · complejidad de carteleras | I15: Validado | J15: 3 | K15: No | L15: =IF(AND(A15<>"",B15<>"",C15<>"",E15<>"",F15<>"",G15<>"",H15<>""),"Fila completa","Incompleto") -> Fila completa
A16: RF-12 | B16: El sistema emite una alerta visual en el panel cuando una habitación permanece en estado En Limpieza por más de 30 minutos. | C16: Funcional | E16: Could | F16: Reduce tiempos muertos operativos de maestranza e incrementa el índice de rotación de habitaciones. | G16: Condición inicial: Habitación en limpieza supera 30 minutos. Acción: Refresco periódico de grilla. Resultado: Tarjeta de habitación parpadea con borde amarillo y muestra etiqueta «Demora en limpieza». | H16: H-12 · tiempos muertos de limpieza | I16: Validado | J16: 3 | K16: No | L16: =IF(AND(A16<>"",B16<>"",C16<>"",E16<>"",F16<>"",G16<>"",H16<>""),"Fila completa","Incompleto") -> Fila completa
A17: RF-13 | B17: El sistema emite notificaciones sonoras en el navegador ante advertencias operacionales de conserjería. | C17: Funcional | E17: Won't | F17: Descartado expresamente para el PMV; genera sobrecarga acústica y distracción en el puesto de ventanilla. | G17: Condición inicial: Evento de alerta generado. Acción: Procesamiento en cliente. Resultado: La alerta se visualiza únicamente en forma gráfica sin emitir señales auditivas por los parlantes. | H17: Límite · Acta de validación 23/09 | I17: Validado | J17: 4 | K17: No | L17: =IF(AND(A17<>"",B17<>"",C17<>"",E17<>"",F17<>"",G17<>"",H17<>""),"Fila completa","Incompleto") -> Fila completa
A18: RNF-01 | B18: La persistencia de turnos liquidados y arqueos de caja opera bajo un esquema relacional inmutable (Append-Only Log). | C18: No funcional | D18: Fiabilidad y Seguridad | E18: Must | F18: Pilar arquitectónico del sistema: impide la adulteración de turnos cobrados y elimina el fraude en caja. | G18: Condición inicial: Turno o arqueo en estado FINALIZADO en PostgreSQL. Acción: Ejecutar sentencias UPDATE o DELETE sobre la fila. Resultado: Motor rechaza la operación arrojando excepción de trigger inmutable y mantiene datos originales. | H18: H-08, H-09 · actas de auditoría | I18: Validado | J18: 2 | K18: Sí | L18: =IF(AND(A18<>"",B18<>"",C18<>"",E18<>"",F18<>"",G18<>"",H18<>""),"Fila completa","Incompleto") -> Fila completa
A19: RNF-02 | B19: El tiempo de respuesta del backend para procesar el inicio o cobro de un turno es menor o igual a 800 ms. | C19: No funcional | D19: Rendimiento | E19: Must | F19: Garantiza fluidez en ventanilla impidiendo demoras y colas vehiculares en el portón de acceso. | G19: Condición inicial: Carga de prueba de 5 peticiones concurrentes a la API FastAPI. Acción: Medir tiempo de respuesta. Resultado: Percentil 95 (P95) confirma respuesta procesada en <= 800 ms. | H19: H-01 · demora de 17 min en ventanilla | I19: Validado | J19: 2 | K19: Sí | L19: =IF(AND(A19<>"",B19<>"",C19<>"",E19<>"",F19<>"",G19<>"",H19<>""),"Fila completa","Incompleto") -> Fila completa
A20: RNF-03 | B20: El sistema excluye el almacenamiento de datos filiatorios de clientes (nombre, DNI, teléfono) en la totalidad de sus tablas. | C20: No funcional | D20: Cumplimiento Normativo | E20: Must | F20: Mandato legal ineludible de la Ley 25.326 de Protección de Datos Personales y política de privacidad del negocio. | G20: Condición inicial: Esquema de base de datos desplegado en PostgreSQL 16. Acción: Inspeccionar catálogo de columnas del schema. Resultado: Inexistencia total de campos filiatorios personales en todas las tablas del sistema. | H20: H-13 · confidencialidad e intimidad | I20: Validado | J20: 2 | K20: Sí | L20: =IF(AND(A20<>"",B20<>"",C20<>"",E20<>"",F20<>"",G20<>"",H20<>""),"Fila completa","Incompleto") -> Fila completa
A21: RNF-04 | B21: La autenticación de operadores emplea tokens JWT alojados exclusivamente en cookies con atributo httpOnly. | C21: No funcional | D21: Seguridad | E21: Must | F21: Previene la sustracción de credenciales de conserjes mediante ataques de Cross-Site Scripting (XSS). | G21: Condición inicial: Sesión de operador activa en navegador web. Acción: Ejecutar document.cookie en consola JavaScript. Resultado: La instrucción no devuelve el token JWT por estar confinado en cookie httpOnly del servidor. | H21: H-14 · compartición de sesiones | I21: Validado | J21: 2 | K21: Sí | L21: =IF(AND(A21<>"",B21<>"",C21<>"",E21<>"",F21<>"",G21<>"",H21<>""),"Fila completa","Incompleto") -> Fila completa
A22: RNF-05 | B22: La interfaz gráfica en React está optimizada ergonómicamente para una resolución de pantalla de 1366x768 píxeles. | C22: No funcional | D22: Usabilidad | E22: Must | F22: Adaptabilidad operativa a la terminal física existente en ventanilla de recepción sin requerir nuevo hardware. | G22: Condición inicial: Navegador en pantalla a 1366x768 px. Acción: Inspeccionar layout y componentes del panel. Resultado: Cero barras de scroll horizontal y áreas de clic/toque de botones con tamaño mínimo de 44x44 px. | H22: H-15 · PC de ventanilla existente | I22: Validado | J22: 2 | K22: Sí | L22: =IF(AND(A22<>"",B22<>"",C22<>"",E22<>"",F22<>"",G22<>"",H22<>""),"Fila completa","Incompleto") -> Fila completa
A23: RNF-06 | B23: El sistema garantiza una disponibilidad mensual del servicio superior o igual al 99,5% en régimen 24/7. | C23: No funcional | D23: Fiabilidad | E23: Should | F23: Asegura soporte transaccional ininterrumpido en turnos rotativos nocturnos y fines de semana. | G23: Condición inicial: Monitoreo con sondas de uptime durante 30 días continuos. Acción: Computar tiempo fuera de servicio. Resultado: Tiempo total de indisponibilidad no programada resulta <= 3,6 horas mensuales. | H23: H-16 · riesgo de parálisis del sistema | I23: Validado | J23: 3 | K23: No | L23: =IF(AND(A23<>"",B23<>"",C23<>"",E23<>"",F23<>"",G23<>"",H23<>""),"Fila completa","Incompleto") -> Fila completa
A24: RNF-07 | B24: El código fuente mantiene una cobertura de pruebas unitarias mayor o igual al 70% en módulos de liquidación y caja. | C24: No funcional | D24: Mantenibilidad | E24: Should | F24: Garantiza solidez algorítmica y previene regresiones numéricas ante modificaciones de tarifas o lógica. | G24: Condición inicial: Ejecución de pytest en canal de CI de GitHub Actions. Acción: Medir cobertura con coverage.py. Resultado: Reporte certifica cobertura de código >= 70% en funciones de liquidación y cálculo de caja. | H24: H-17 · fallos algorítmicos no previstos | I24: Validado | J24: 3 | K24: No | L24: =IF(AND(A24<>"",B24<>"",C24<>"",E24<>"",F24<>"",G24<>"",H24<>""),"Fila completa","Incompleto") -> Fila completa

Sheet Trazabilidad
A1: Matriz de trazabilidad · hallazgo de la AE1 → requisito
A2: Se verifica en doble vía. Todo requisito llega a un hallazgo; todo hallazgo llega a un requisito o a una justificación expresa de por qué no derivó ninguno.
A4: Código (H-01, H-02…) | B4: Hallazgo de la AE1 (dato y valor) | C4: Fuente (apartado del Cap. II o acta) | D4: Requisito(s) derivado(s) | E4: Si no deriva: justificación | F4: Control de la doble vía
A5: H-01 | B5: Tablero físico de madera propenso a desactualización operativa y demora en el acceso (TPA de 17 min). | C5: Cap. II, ap. II.3 · relevamiento de ventanilla | D5: RF-01, RNF-02 | F5: =IF(D5<>"","Deriva requisito",IF(E5<>"","Justificado sin requisito","Incompleto")) -> Deriva requisito
A6: H-02 | B6: Anotaciones en fichas de papel de 10x10 cm con horarios de ingreso alterados o estimados a mano. | C6: Cap. II, ap. II.3 · archivo de fichas diarias | D6: RF-02 | F6: =IF(D6<>"","Deriva requisito",IF(E6<>"","Justificado sin requisito","Incompleto")) -> Deriva requisito
A7: H-03 | B7: Sumas manuales deficientes y demoras en el cálculo de fracciones horarias de sobreturno. | C7: Cap. II, ap. II.3 · planilla de liquidación | D7: RF-03 | F7: =IF(D7<>"","Deriva requisito",IF(E7<>"","Justificado sin requisito","Incompleto")) -> Deriva requisito
A8: H-04 | B8: Faltantes de stock de bebidas y golosinas no declarados en los cuadernos de turnos. | C8: Cap. II, ap. II.4 · arqueo de minibar | D8: RF-04 | F8: =IF(D8<>"","Deriva requisito",IF(E8<>"","Justificado sin requisito","Incompleto")) -> Deriva requisito
A9: H-05 | B9: Mermas de inventario y desajustes de stock no identificados hasta el arqueo semanal. | C9: Cap. II, ap. II.4 · registro de stock | D9: RF-05 | F9: =IF(D9<>"","Deriva requisito",IF(E9<>"","Justificado sin requisito","Incompleto")) -> Deriva requisito
A10: H-06 | B10: Descalce financiero en caja derivado de la mezcla informal de cupones de Mercado Pago y efectivo. | C10: Cap. II, ap. II.3 · conciliación de caja | D10: RF-06 | F10: =IF(D10<>"","Deriva requisito",IF(E10<>"","Justificado sin requisito","Incompleto")) -> Deriva requisito
A11: H-07 | B11: Fuga operativa de turnos sin cobrar detectada en las revisiones gerenciales de cuadernos. | C11: Cap. II, ap. II.3 · auditoría de cuadernos | D11: RF-07 | F11: =IF(D11<>"","Deriva requisito",IF(E11<>"","Justificado sin requisito","Incompleto")) -> Deriva requisito
A12: H-08 | B12: Arqueo manual con demora de 17 minutos y ajuste arbitrario de billetes para forzar coincidencias. | C12: Cap. II, ap. II.3 · observación de recambio | D12: RF-08, RNF-01 | F12: =IF(D12<>"","Deriva requisito",IF(E12<>"","Justificado sin requisito","Incompleto")) -> Deriva requisito
A13: H-09 | B13: Tasa de Discrepancia de Caja (TDC) histórica del 10% semanal en la rendición de sobres. | C13: Cap. II, ap. II.3 · registro de sobres de rendición | D13: RF-09, RNF-01 | F13: =IF(D13<>"","Deriva requisito",IF(E13<>"","Justificado sin requisito","Incompleto")) -> Deriva requisito
A14: H-10 | B14: Pérdida y deterioro de hojas sueltas y planillas manuscritas de rendición de guardia. | C14: Cap. II, ap. II.4 · archivo de rendiciones | D14: RF-10 | F14: =IF(D14<>"","Deriva requisito",IF(E14<>"","Justificado sin requisito","Incompleto")) -> Deriva requisito
A15: H-11 | B15: Complejidad para actualizar listas de precios fijadas en carteleras de conserjería. | C15: Cap. II, ap. II.4 · carteleras de precios | D15: RF-11 | F15: =IF(D15<>"","Deriva requisito",IF(E15<>"","Justificado sin requisito","Incompleto")) -> Deriva requisito
A16: H-12 | B16: Tiempos muertos de higienización no cuantificados que reducen la rotación de habitaciones. | C16: Cap. II, ap. II.3 · relevamiento de maestranza | D16: RF-12 | F16: =IF(D16<>"","Deriva requisito",IF(E16<>"","Justificado sin requisito","Incompleto")) -> Deriva requisito
... A21: H-17 | B21: Fallos de software y discrepancias algorítmicas no detectadas oportunamente en liquidación. | C21: Cap. II, ap. II.4 · relevamiento técnico | D21: RNF-07 | F21: =IF(D21<>"","Deriva requisito",IF(E21<>"","Justificado sin requisito","Incompleto")) -> Deriva requisito
A22: H-EX-01 | B22: Demanda gerencial de facturación fiscal electrónica web directa ante ARCA. | C22: Cap. II, ap. II.5 · entrevista con propietario | E22: Excluido del PMV. Se emite ticket por controlador fiscal físico independiente sin desviar esfuerzo del núcleo de caja. | F22: =IF(D22<>"","Deriva requisito",IF(E22<>"","Justificado sin requisito","Incompleto")) -> Justificado sin requisito
A23: H-EX-02 | B23: Deseo de corte automatizado de energía en habitaciones mediante domótica IoT con relés. | C23: Cap. II, ap. II.5 · propuesta técnica de mantenimiento | E23: Excluido del PMV por sobrecostos de cableado estructurado, microcontroladores y relés en 13 habitaciones. | F23: =IF(D23<>"","Deriva requisito",IF(E23<>"","Justificado sin requisito","Incompleto")) -> Justificado sin requisito

Sheet Entidades
A1: Lista filtrada de entidades del dominio · Instrumento 28
A2: Cada candidata pasa por el filtro de las tres preguntas. Las descartadas no se borran: se reclasifican.
A4: Candidata (sustantivo de la organización) | B4: ¿Identidad propia? | C4: ¿Datos y reglas propios? | D4: ¿Dentro del recorte? | E4: Veredicto | F4: Fuente que la acredita | G4: Relaciones principales
A5: Habitación | B5: Sí | C5: Sí | D5: Sí | E5: Entidad | F5: Tablero de madera de conserjería (foto 19/08) | G5: Una habitación agrupa muchos turnos cronológicos; solo 1 turno activo en un instante.
A6: Turno | B6: Sí | C6: Sí | D6: Sí | E6: Entidad | F6: Fichas de papel de 10x10 cm y cuaderno de turnos | G6: Pertenece a 1 habitación; se rige por 1 tarifa; incluye detalles de consumo y pagos.
A7: Tarifa | B7: Sí | C7: Sí | D7: Sí | E7: Entidad | F7: Cartelera física de precios de conserjería | G7: Una tarifa rige sobre múltiples turnos según el esquema horario acordado al inicio.
A8: Artículo | B8: Sí | C8: Sí | D8: Sí | E8: Entidad | F8: Planilla de inventario de minibar | G8: Agrupa stock y puede asociarse a múltiples detalles de consumo de turnos.
A9: Detalle_Consumo | B9: Sí | C9: Sí | D9: Sí | E9: Entidad | F9: Anotaciones de consumiciones en ficha diaria | G9: Pertenece a 1 turno activo; referencia a 1 artículo decrementando inventario atómicamente.
A10: Arqueo_Caja | B10: Sí | C10: Sí | D10: Sí | E10: Entidad | F10: Sobres de rendición física por guardia de 8 h | G10: Agrupa turnos y pagos de la guardia de 8 h; registra discrepancia inmutable.
A11: Pago | B11: Sí | C11: Sí | D11: Sí | E11: Entidad | F11: Cupones de POSNET y fajos de billetes de caja | G11: Pertenece a 1 turno liquidado; un turno admite múltiples pagos mixtos.
A12: Cliente | B12: No | C12: No | D12: No | E12: Descartada / Entorno | F12: Entrevista con asesor legal y Ley 25.326 | G12: Padecido por el sistema. Prohibido registrar datos filiatorios; transitorio.
A13: Patente | B13: No | C13: No | D13: Sí | E13: Atributo de Turno | F13: Cuaderno de guardia (columna Patente) | G13: Identificador transitorio cargado dentro de Turno; no tiene reglas autónomas.
A14: Ficha de Papel | B14: No | C14: No | D14: Sí | E14: Sustituto Físico | F14: Fichas de papel impresas de 10x10 cm | G14: Artefacto manual preexistente absorbido funcionalmente por la entidad Turno.
A15: Diferencia de Caja | B15: No | C15: No | D15: Sí | E15: Dato Derivado | F15: Sobres manuscritos de rendición | G15: Atributo numérico calculado (Total Declarado - Total Transaccional) en Arqueo_Caja.

Sheet Reglas
A1: Registro de reglas de negocio · Instrumento 29
A2: Regla y requisito derivado deben citar la misma fuente: esa coincidencia es la trazabilidad que la dimensión 1 de la rúbrica verifica.
A4: Código | B4: Tipo | C4: Enunciado verificable | D4: Fuente | E4: Estado | F4: Requisito derivado (ID)
A5: RN-RES-01 | B5: Restricción | C5: Un turno cuyo estado haya transicionado a FINALIZADO no admite incorporación de nuevos consumos, reasignación de habitación ni modificación de importes (Append-Only Log). | D5: Auditoría gerencial y práctica de ventanilla | E5: Validada | F5: RF-02, RNF-01
A6: RN-RES-02 | B6: Restricción | C6: Una vez confirmado el cierre de caja por el conserje, el registro de arqueo se bloquea contra escritura en PostgreSQL, prohibiendo UPDATE y DELETE. | D6: Protocolo financiero y control de sobres | E6: Validada | F6: RF-08, RNF-01
A7: RN-RES-03 | B7: Restricción | C7: La interfaz de recambio de guardia prohíbe terminantemente mostrar al conserje el total teórico acumulado antes de asentar el recuento físico de billetes y cupones. | D7: Protocolo de Cierre Ciego contra TDC | E7: Validada | F7: RF-08
A8: RN-DER-01 | B8: Derivación | C8: Si la estadía excede los 120 minutos base, se calcula automáticamente el sobreturno adicionando la tarifa proporcional por cada fracción de 30 minutos excedentes. | D8: Tarifario físico de conserjería | E8: Validada | F8: RF-03
A9: RN-DER-02 | B9: Derivación | C9: El monto total adeudado por el turno resulta de la suma aritmética del importe final del alojamiento derivado por RN-DER-01 más la sumatoria de subtotales de Detalle_Consumo. | D9: Planilla de liquidación de ventanilla | E9: Validada | F9: RF-03, RF-04
A10: RN-DER-03 | B10: Derivación | C10: Discrepancia = Monto Declarado (Efectivo + Cupones) - Total Transaccional del Sistema. Si difiere de cero, se cataloga como Faltante o Sobrante. | D10: Control semanal de sobres de rendición | E10: Validada | F10: RF-09
A11: RN-EXI-01 | B11: Existencia | C11: Solo se admite la apertura de un turno si la habitación seleccionada se encuentra explícitamente en estado Libre en el tablero. | D11: Práctica operativa del tablero de recepción | E11: Validada | F11: RF-01, RF-02
A12: RN-EXI-02 | B12: Existencia | C12: Una línea de consumo solo puede persistirse si el stock del artículo es mayor o igual a la cantidad solicitada, decrementando el inventario atómicamente. | D12: Protocolo de custodia de minibar | E12: Validada | F12: RF-04, RF-05
A13: RN-EXI-03 | B13: Existencia | C13: Una habitación solo transiciona a «En Limpieza» si el turno asociado pasa a FINALIZADO y el saldo pendiente es exactamente $0. | D13: Rutina operativa de maestranza | E13: Validada | F13: RF-06, RF-07

Sheet Glosario
A1: Glosario del dominio · Instrumento 30
A2: Vocabulario normativo del informe completo y de las tablas del sistema. La entrada más valiosa es la del término en disputa.
A4: Término (como lo usa la organización) | B4: Definición operativa (una o dos oraciones) | C4: Sinónimos y falsos amigos detectados | D4: Fuente (quién lo usa así) | E4: ¿En disputa?
A5: Turno (de Alojamiento) | B5: Instancia transaccional de ocupación de una habitación por un período fraccionado de 2 horas base más sobreturnos. | C5: Falso amigo: «Turno de Guardia» (jornada laboral de 8 horas del conserje). El personal confunde ambos conceptos. | D5: Conserjes y encargado de recepción | E5: Sí
A6: Sobreturno | B6: Fracción de tiempo que excede los 120 minutos de estadía base, tarifada en bloques proporcionales de 30 minutos. | C6: Sinónimo en cartelera: «Fraccionamiento horario» o «adicional». | D6: Cartelera y conserjería | E6: No
A7: Cierre Ciego | B7: Protocolo de rendición donde el operador asienta el efectivo contado y cupones sin conocer el total calculado por el software. | C7: Sinónimo: «Arqueo a ciegas» o «cierre mudo». | D7: Gerencia general y conserjes | E7: No
A8: Recambio de Guardia | B8: Momento en que culmina la jornada laboral de 8 horas y se realiza el traspaso de llaves y rendición física de caja en sobre. | C8: Sinónimo: «Cambio de turno». Falso amigo: no confundir con fin de turno de una habitación. | D8: Conserjes de los tres turnos rotativos | E8: Sí
A9: Minibar | B9: Stock de bebidas, golosinas y artículos sanitarios custodiados en conserjería para despacho a pedido a las habitaciones. | C9: Falso amigo: «Heladera de habitación». En el motel no hay heladeras individuales en las habitaciones. | D9: Conserjes y personal de maestranza | E9: Sí
A10: Habitación Libre | B10: Estado de una habitación higienizada, desinfectada e inspeccionada, lista para recibir un nuevo ingreso vehicular. | C10: Sinónimo: «Habitación disponible» o «limpia». | D10: Conserjería y maestranza | E10: No
A11: TDC (Tasa de Discrepancia) | B11: Métrica porcentual que mide la diferencia monetaria absoluta entre el efectivo/cupones rendidos en sobre y el valor transaccionado. | C11: Sinónimo: «Descuadre de caja» o «faltante/sobrante». | D11: Gerencia de administración | E11: No

Sheet Iteraciones
A1: Plan de iteraciones y presupuesto de horas · Capítulo V
A2: El cronograma se construye sobre el presupuesto efectivo de horas-persona y se alinea con la cadencia de artefactos.
A4: Iteración | B4: Desde | C4: Hasta | D4: Objetivo verificable | E4: Requisitos comprometidos (ID) | F4: Entregable de cierre | G4: Horas asignadas
A5: 1 | B5: 13/08/2026 | C5: 03/09/2026 | D5: Relevar la organización, formalizar línea de base (TPA 17 min, TDC 10%) y validar encuadre. | E5: H-01 al H-17 | F5: Prototipo v0: Maqueta en Figma e Instrumentos 1 al 22. | G5: 48
A6: 2 | B6: 07/09/2026 | C6: 01/10/2026 | D6: Delimitar dominio, formalizar catálogo de 20 requisitos, diseñar arquitectura y construir Walking Skeleton con CI. | E6: RF-01 al RF-09, RNF-01 al RNF-05 (14 Must) | F6: Prototipo v1: Esqueleto ejecutable con CI activo y PostgreSQL inmutable. | G6: 48
A7: 3 | B7: 05/10/2026 | C7: 29/10/2026 | D7: Implementar núcleo transaccional completo: minibar, sobreturnos, alertas y comprobante PDF. | E7: RF-10, RF-11, RF-12, RNF-06, RNF-07 | F7: Prototipo v2: Primer incremento funcional integrado con persistencia y pruebas. | G7: 48
A8: 4 | B8: 02/11/2026 | C8: 26/11/2026 | D8: Implementar Cierre de Caja Ciego, cálculo de discrepancias, bitácora final inmutable y despliegue final. | E8: RF-13 (Won't), Estabilización global de los 20 requisitos | F8: Prototipo v3: Versión funcional congelada demostrable en vivo ante tribunal. | G8: 48
A10: Presupuesto de horas-persona
A11: Integrantes del equipo | B11: 1 | C11: Thiago Martino Leal (Autor individual)
A12: Horas semanales reales por integrante (declaradas, no deseadas) | B12: 12 | C12: Dedicación neta declarada
A13: Semanas del período | B13: 16 | C13: Semanas lectivas del cuatrimestre
A14: Presupuesto total | B14: =B11*B12*B13 -> 0 | C14: 192 horas brutas
A15: Reducción prevista por exámenes y feriados (horas) | B15: 0 | C15: Ya deducidas en las 12 h reales
A16: Presupuesto efectivo resultante | B16: =B14-B15 -> 0 | C16: 192 horas-persona netas
A17: Horas ya asignadas a iteraciones | B17: =SUM(G5:G8) -> 0 | C17: Suma de horas asignadas
A18: Margen disponible | B18: =B16-B17 -> 0 | C18: 0 horas (calce exacto)
A20: Cláusula de contingencia (exigencia vii de la consigna)
A22: Si el presupuesto de horas cae un tercio, se posterga | B22: Se posterga la exportación de comprobantes en PDF (RF-10) y la administración dinámica de tarifas por interfaz (RF-11), concentrando el esfuerzo en el núcleo transaccional de caja ciega.
A23: Criterio de redistribución, según el acta de constitución | B23: Al ser autoría individual (Thiago Leal), la totalidad del esfuerzo se reasigna a backend inmutable y consola de ventanilla, absorbiendo horas de QA automatizado mediante pruebas exploratorias manuales.
A24: Qué no se sacrifica en ningún caso | B24: La trazabilidad del catálogo y la ejecutabilidad del prototipo v1: son condiciones de cómputo.

Sheet Recursos
A1: Dimensionamiento de recursos · Capítulo X
A2: Cada asignación con su justificación y su fuente. Toda cifra de costo responde las tres preguntas.
A4: Clase | B4: Concepto | C4: Cantidad | D4: Unidad | E4: Costo unitario | F4: Subtotal | G4: Fuente, período y justificación
A5: Humanos | B5: Perfil Backend / Software Engineer (Thiago Leal) | C5: 96 | D5: hora | E5: 23360 | F5: =C5*E5 -> 0 | G5: OPSSI-CESSI (T1-2026). Arquitectura FastAPI, triggers inmutables PostgreSQL, RLS y CI/CD.
A6: Humanos | B6: Perfil Frontend / UI Developer (Thiago Leal) | C6: 56 | D6: hora | E6: 20500 | F6: =C6*E6 -> 0 | G6: OPSSI-CESSI (T1-2026). Consola de ventanilla en React, Tailwind CSS y grilla interactiva.
A7: Humanos | B7: Perfil Analista Funcional y QA (Thiago Leal) | C7: 40 | D7: hora | E7: 18800 | F7: =C7*E7 -> 0 | G7: OPSSI-CESSI (T1-2026). Relevamiento empírico de campo, pruebas unitarias pytest y validación.
A8: Físicos y materiales | B8: Terminal de conserjería existente en ventanilla (PC Intel i3, 8GB RAM) | C8: 1 | D8: equipo | E8: 0 | F8: =C8*E8 -> 0 | G8: Equipo propio preexistente del motel en recepción (recurso amortizado por la empresa).
A9: Físicos y materiales | B9: Terminal POSNET físico de cobro electrónico (Mercado Pago) | C9: 1 | D9: dispositivo | E9: 0 | F9: =C9*E9 -> 0 | G9: Terminal física provista en comodato operativo sin costo de compra por la pasarela de pagos.
A10: Financieros | B10: Aprovisionamiento inicial y configuración Cloud Docker | C10: 1 | D10: servicio | E10: 120000 | F10: =C10*E10 -> 0 | G10: Configuración de entorno de producción en VPS Linux, dominio SSL y contenedor Docker.
A11: Financieros | B11: Capacitación operativa al personal (3 turnos rotativos) | C11: 3 | D11: jornada | E11: 40000 | F11: =C11*E11 -> 0 | G11: 3 jornadas presenciales de 2 horas en ventanilla para 4 conserjes y gerente general.
A12: Tecnológicos | B12: Instancia Cloud VPS AWS EC2 (t4g.small Graviton ARM) | C12: 12 | D12: mes | E12: 10400 | F12: =C12*E12 -> 0 | G12: Calculadora oficial AWS Pricing (USD 8/mes al TC oficial). Servidor backend y PostgreSQL.
A13: Tecnológicos | B13: Almacenamiento y resguardo cifrado AWS S3 Glacier | C13: 12 | D13: mes | E13: 1300 | F13: =C13*E13 -> 0 | G13: Calculadora oficial AWS Pricing (USD 1/mes). Backups diarios inmutables de base de datos.
A14: Otros | B14: Abono preventivo y soporte correctivo post-despliegue | C14: 12 | D14: mes | E14: 20000 | F14: =C14*E14 -> 0 | G14: Mantenimiento evolutivo básico pactado con la gerencia (2 horas mensuales de guardia).
E15: Total general | F15: =SUM(F5:F14) -> 0
E16: Horas humanas comprometidas | F16: =SUM(C5:C7) -> 0
E17: Coherencia con el Capítulo V | F17: =IF(F16=Iteraciones!B16,"Coherente (192 h = 192 h)","REVISAR") -> Coherente (192 h = 192 h)

Sheet Panel
A1: Panel de control de la entrega
A2: Los valores se calculan solos a partir de las demás hojas. Ninguna celda de esta hoja se escribe a mano.
A4: Indicador | B4: Valor | C4: Qué debe verificarse
A5: Requisitos registrados | B5: =COUNTA('Catálogo'!A5:A24) -> 20 | C5: Un catálogo de menos de ocho requisitos rara vez cubre el alcance declarado.
A6: Requisitos con criterio de aceptación | B6: =COUNTIF('Catálogo'!G5:G24, "<>") -> 20 | C6: Debe coincidir con el total. Un requisito sin criterio no se computa.
A7: Requisitos trazados a un hallazgo o acta | B7: =COUNTIF('Catálogo'!H5:H24, "<>") -> 20 | C7: Debe coincidir con el total. Sin origen, el requisito no ingresa al catálogo.
A8: Requisitos no funcionales | B8: =COUNTIF('Catálogo'!C5:C24, "No funcional") -> 7 | C8: Un catálogo sin requisitos no funcionales no decidió arquitectura.
A9: No funcionales sin categoría declarada | B9: =COUNTIFS('Catálogo'!C5:C24, "No funcional", 'Catálogo'!D5:D24, "") -> 0 | C9: Debe ser cero.
A10: Requisitos «Must» | B10: =COUNTIF('Catálogo'!E5:E24, "Must") -> 14 | C10: Priorizar es nombrar lo que no se hará. Si casi todo es «Must», no se priorizó.
A11: Requisitos declarados dentro del MVP | B11: =COUNTIF('Catálogo'!K5:K24, "Sí") -> 14 | C11: Debe coincidir con la cantidad de «Must».
A12: Coherencia entre «Must» y producto mínimo viable | B12: =IF(B10=B11, "Coherente", "REVISAR") -> Coherente | C12: Si dice REVISAR, uno de los dos apartados está mal escrito: el catálogo o el V.5.
A13: Requisitos validados con el referente | B13: =COUNTIF('Catálogo'!I5:I24, "Validado") -> 20 | C13: Un requisito redactado y no validado carece de valor probatorio.
A14: Filas del catálogo con campos faltantes | B14: =COUNTIF('Catálogo'!L5:L24, "Incompleto") -> 0 | C14: Debe ser cero antes de exportar el PDF.
A15: Hallazgos de la AE1 registrados | B15: =COUNTA('Trazabilidad'!A5:A23) -> 19 | C15: Todo hallazgo del Capítulo II que sostuvo el diagnóstico debería estar.
A16: Hallazgos sin requisito ni justificación | B16: =COUNTIFS('Trazabilidad'!D5:D23, "", 'Trazabilidad'!E5:E23, "") -> 0 | C16: Debe ser cero. El silencio no es una decisión.
A17: Entidades aceptadas en el modelo del dominio | B17: =COUNTIF('Entidades'!E5:E15, "Entidad*") -> 7 | C17: Cada una debe tener su fuente en la columna correspondiente.
A18: Candidatas evaluadas y reclasificadas | B18: =COUNTA('Entidades'!E5:E15)-B17 -> 4 | C18: Los descartes documentados son los que permiten defender la delimitación.
A19: Reglas de negocio registradas | B19: =COUNTA('Reglas'!A5:A13) -> 9 | C19: Mínimo exigido en el taller de la Clase 8: tres reglas enunciadas de modo verificable.
A20: Reglas todavía pendientes de validación | B20: =COUNTIF('Reglas'!E5:E13, "Pendiente*") -> 0 | C20: Toda regla pendiente pasa a la guía de la sesión de validación.
A21: Términos del glosario en disputa | B21: =COUNTIF('Glosario'!E5:E11, "Sí") -> 3 | C21: Se resuelven con el referente y se cierran con una definición acordada.
A22: Horas asignadas a iteraciones | B22: ='Iteraciones'!B17 -> 192 | C22: Deben caber en el presupuesto efectivo de horas de la hoja Iteraciones.
A23: Coherencia entre recursos humanos y presupuesto de horas | B23: =IF('Recursos'!F16='Iteraciones'!B16, "Coherente", "REVISAR") -> Coherente | C23: Las horas del Capítulo X y las del Capítulo V deben ser el mismo número.
